dbcluster/__init__.py
dbcluster/container.py
dbcluster/sacontainer.py
dbcluster-0.1.data/data/README.md
dbcluster-0.1.data/data/dev-requirements.txt
dbcluster-0.1.data/data/requirements.txt
dbcluster-0.1.dist-info/LICENSE
dbcluster-0.1.dist-info/METADATA
dbcluster-0.1.dist-info/WHEEL
dbcluster-0.1.dist-info/top_level.txt
dbcluster-0.1.dist-info/RECORD
