Metadata-Version: 2.1
Name: dbcluster
Version: 0.1
Summary: Database Cluster Session Manager
Home-page: http://github.com/krishardy/dbcluster
Author: Kris Hardy
Author-email: kris@abqsoft.com
License: Apache 2.0
Download-URL: https://github.com/krishardy/dbcluster/archive/0.1.tar.gz
Platform: UNKNOWN
Classifier: Development Status :: 2 - Pre-Alpha
Classifier: Intended Audience :: Developers
Classifier: License :: OSI Approved :: Apache Software License
Classifier: Operating System :: OS Independent
Classifier: Programming Language :: Python
Classifier: Programming Language :: Python :: 2
Classifier: Programming Language :: Python :: 2.7
Classifier: Programming Language :: Python :: 3
Classifier: Programming Language :: Python :: 3.6
Classifier: Topic :: Database
Classifier: Topic :: Software Development :: Libraries
Requires-Dist: future
